<?xml version="1.0" encoding="UTF-8"?>
<objects serializationModel="Studio.02.02.00">
	<object class="AudioFile" id="{3324f579-70eb-4ebd-8fd7-65a649b511de}">
		<property name="assetPath">
			<value>Footsteps/Footsteps_WaterHeavy_5.wav</value>
		</property>
		<property name="frequencyInKHz">
			<value>48</value>
		</property>
		<property name="channelCount">
			<value>2</value>
		</property>
		<property name="length">
			<value>1.5</value>
		</property>
		<relationship name="masterAssetFolder">
			<destination>{05390b02-8d1a-4f09-baef-ce3b37da9bf7}</destination>
		</relationship>
	</object>
</objects>
